odoo/addons/account_check_report/README.rst
odoo/addons/account_check_report/__init__.py
odoo/addons/account_check_report/__manifest__.py
odoo/addons/account_check_report/i18n/account_check_report.pot
odoo/addons/account_check_report/i18n/pt.po
odoo/addons/account_check_report/readme/CONTRIBUTORS.rst
odoo/addons/account_check_report/readme/DESCRIPTION.rst
odoo/addons/account_check_report/report/__init__.py
odoo/addons/account_check_report/report/account_check_report.xml
odoo/addons/account_check_report/report/report_helper.py
odoo/addons/account_check_report/static/description/icon.png
odoo/addons/account_check_report/static/description/index.html
odoo12_addon_account_check_report-12.0.1.0.0.99.dev5.dist-info/METADATA
odoo12_addon_account_check_report-12.0.1.0.0.99.dev5.dist-info/WHEEL
odoo12_addon_account_check_report-12.0.1.0.0.99.dev5.dist-info/top_level.txt
odoo12_addon_account_check_report-12.0.1.0.0.99.dev5.dist-info/RECORD
